ecg_plot.py
ecg_plot/__init__.py
ecg_plot/ecg_plot.py
ecg_plot/ecg_plot_bak.py
src/__init__.py
src/ecg_plot.py
ecg_plot-0.2.8.dist-info/LICENCE
ecg_plot-0.2.8.dist-info/METADATA
ecg_plot-0.2.8.dist-info/WHEEL
ecg_plot-0.2.8.dist-info/top_level.txt
ecg_plot-0.2.8.dist-info/RECORD
