Metadata-Version: 2.1
Name: ecg-plot
Version: 0.2.8
Summary: Plot standard ECG chart from data
Home-page: https://github.com/dy1901/ecg_plot
Author: dy1901
Author-email: dy1901@gmail.com
License: MIT License
Platform: UNKNOWN
Classifier: Programming Language :: Python :: 3
Classifier: License :: OSI Approved :: MIT License
Classifier: Operating System :: OS Independent
